<?xml version="1.0" encoding="UTF-8"?><SpineML xmlns:UL="http://www.shef.ac.uk/SpineMLNetworkLayer" xmlns:xsi="http://www.w3.org/2001/XMLSchema-instance" xmlns="http://www.shef.ac.uk/SpineMLExperimentLayer" xsi:schemaLocation="http://www.shef.ac.uk/SpineMLNetworkLayer SpineMLNetworkLayer.xsd http://www.shef.ac.uk/SpineMLExperimentLayer SpineMLExperimentLayer.xsd"><Experiment name="Steady state" description="Run model with just the background input; no selected channel"><Model network_layer_url="model.xml"/><Simulation duration="1" preferred_simulator="BRAHMS"><EulerIntegration dt="0.1"/></Simulation><ConstantInput target="Background c3" port="spike" value="3" name="BG Poisson Spikes" rate_based_input="poisson" rate_seed="123"/><LogOutput name="SNr v" target="SNr c2" port="v" start_time="0" end_time="1e+08"/><LogOutput name="SNr spikes" target="SNr c2" port="spike" start_time="0" end_time="1e+08"/><LogOutput name="GPe spikes" target="GPe c2" port="spike" start_time="0" end_time="1e+08"/><LogOutput name="GPe v" target="GPe c2" port="v" start_time="0" end_time="1e+08"/><LogOutput name="D1 v" target="D1 MSN c2" port="v" start_time="0" end_time="1e+08"/><LogOutput name="D2 v" target="D2 MSN c2" port="v" start_time="0" end_time="1e+08"/><LogOutput name="STN v" target="STN c2" port="v" start_time="0" end_time="1e+08"/><LogOutput name="g_ampa to D1" target="Background c3 to D1 MSN c2 Synapse 0 postsynapse" port="g_ampa" start_time="0" end_time="1e+08"/><LogOutput name="g_gaba recurrent" target="D1 MSN c2 to D1 MSN c2 Synapse 0 postsynapse" port="g_gaba" start_time="0" end_time="1e+08"/><LogOutput name="I_gaba recurrent" target="D1 MSN c2 to D1 MSN c2 Synapse 0 postsynapse" port="I_gaba" start_time="0" end_time="1e+08"/></Experiment></SpineML>
